pydnx/__init__.py
pydnx/factory.py
pydnx/model.py
pydnx-0.1.0.dist-info/DESCRIPTION.rst
pydnx-0.1.0.dist-info/METADATA
pydnx-0.1.0.dist-info/RECORD
pydnx-0.1.0.dist-info/WHEEL
pydnx-0.1.0.dist-info/metadata.json
pydnx-0.1.0.dist-info/top_level.txt
